{
	"name": "ODS2Integration",
	"properties": {
		"activities": [
			{
				"name": "PurchaseStaging",
				"type": "ExecuteDataFlow",
				"dependsOn": [
					{
						"activity": "Set LMDT",
						"dependencyConditions": [
							"Succeeded"
						]
					}
				],
				"policy": {
					"timeout": "0.12:00:00",
					"retry": 0,
					"retryIntervalInSeconds": 30,
					"secureOutput": false,
					"secureInput": false
				},
				"typeProperties": {
					"dataflow": {
						"referenceName": "PurchaseStaging",
						"type": "DataFlowReference"
					},
					"compute": {
						"coreCount": 8,
						"computeType": "General"
					},
					"traceLevel": "Fine"
				}
			},
			{
				"name": "DeleteData",
				"type": "Script",
				"dependsOn": [],
				"policy": {
					"timeout": "0.12:00:00",
					"retry": 0,
					"retryIntervalInSeconds": 30,
					"secureOutput": false,
					"secureInput": false
				},
				"userProperties": [],
				"linkedServiceName": {
					"referenceName": "Integration002",
					"type": "LinkedServiceReference"
				},
				"typeProperties": {
					"scripts": [
						{
							"parameters": [
								{
									"name": "schema",
									"type": "String",
									"value": {
										"value": "Integration",
										"type": "Expression"
									},
									"direction": "Input"
								},
								{
									"name": "table",
									"type": "String",
									"value": {
										"value": "Purchase_Staging",
										"type": "Expression"
									},
									"direction": "Input"
								},
								{
									"name": "InsertQuery",
									"type": "String",
									"value": "",
									"direction": "Input"
								},
								{
									"name": "tablename",
									"type": "String",
									"value": "@schema+'.'+@table",
									"direction": "Input"
								},
								{
									"name": "DelQuery",
									"type": "String",
									"value": "",
									"direction": "Input"
								},
								{
									"name": "condition",
									"type": "String",
									"value": "",
									"direction": "Input"
								}
							],
							"type": "Query",
							"text": "set @condition =  'CAST(IngestDatetime AS DATE) < DATEADD(day, -30, Getdate())'\n\nset @InsertQuery = 'Insert into dbo.DeleteLog ([Table Name], [Delete Table pk], [Complete Date]) select '''+@tablename+''' as [Table Name], Purchase Staging Key, Getdate() as [Complete Date] from '+@tablename+' where '+@condition\nset @DelQuery = 'delete from ' + @tablename + ' where '+ @condition\n\nEXECUTE sp_executesql @InsertQuery\nEXECUTE sp_executesql @DelQuery"
						}
					],
					"scriptBlockExecutionTimeout": "02:00:00"
				}
			},
			{
				"name": "Script1",
				"type": "Script",
				"dependsOn": [
					{
						"activity": "DeleteData",
						"dependencyConditions": [
							"Succeeded"
						]
					}
				],
				"policy": {
					"timeout": "0.12:00:00",
					"retry": 0,
					"retryIntervalInSeconds": 30,
					"secureOutput": false,
					"secureInput": false
				},
				"userProperties": [],
				"linkedServiceName": {
					"referenceName": "Integration002",
					"type": "LinkedServiceReference"
				},
				"typeProperties": {
					"scripts": [
						{
							"parameters": [
								{
									"name": "LastModifiedDT",
									"type": "Datetime",
									"value": "",
									"direction": "Output"
								}
							],
							"type": "Query",
							"text": "select @LastModifiedDT = [Last Trigger Datetime] from dbo.MasterTab"
						}
					],
					"scriptBlockExecutionTimeout": "02:00:00"
				}
			},
			{
				"name": "Set LMDT",
				"type": "SetVariable",
				"dependsOn": [
					{
						"activity": "Script1",
						"dependencyConditions": [
							"Succeeded"
						]
					}
				],
				"userProperties": [],
				"typeProperties": {
					"variableName": "LastModifiedDT",
					"value": {
						"value": "@activity('Script1').output.outputParameters.LastModifiedDT",
						"type": "Expression"
					}
				}
			}
		],
		"variables": {
			"LastModifyDate": {
				"type": "String"
			},
			"LastModifiedDT": {
				"type": "String"
			},
			"LMDT": {
				"type": "String"
			}
		},
		"annotations": []
	}
}